{
    "common/arc": {
        "description": "方舟核心"
    },
    "jarvis": {
        "description": "J.A.R.V.I.S"
    },
    "project/nightclub": {
        "description": "夜店"
    },
    "project/sneaky": {
        "description": "鬼祟"
    },
    "project/heartbreaker": {
        "description": "碎心者"
    },
    "project/cassanova": {
        "description": "卡萨诺瓦"
    },
    "project/tiger": {
        "description": "老虎"
    },
    "project/midas": {
        "description": "麦得斯"
    },
    "friday": {
        "description": "星期五"
    },
    "environment": {
        "description": "环境变量"
    },
    "common/copper": {
        "description": "静态资源"
    },
    "common/iron": {
        "description": "图标库"
    },
    "common/silver": {
        "description": "通用组件"
    },
    "public": {
        "description": "静态资源目录"
    },
    "website": {
        "description": "文档网站"
    },
    "tsconfig.app.json": {
        "description": "project用"
    },
    "tsconfig.vue.json": {
        "description": "vue-tsc用"
    }
}